claritycore/__init__.py
claritycore/arch/__init__.py
claritycore/arch/arch_util.py
claritycore/arch/components.py
claritycore/arch/hat.py
claritycore/arch/rrdbnet.py
claritycore/cli/__init__.py
claritycore/cli/main.py
claritycore/cli/train.py
claritycore/dataset/__init__.py
claritycore/dataset/datasets.py
claritycore/loss/__init__.py
claritycore/loss/losses.py
claritycore/metric/__init__.py
claritycore/metric/psnr_ssim.py
claritycore/model/__init__.py
claritycore/trainer/__init__.py
claritycore/utils/__init__.py
claritycore/utils/color_util.py
claritycore/utils/common.py
claritycore/utils/preprocess_util.py
claritycore/utils/registry.py
claritycore/utils/set_seed.py
claritycore-0.0.4.dist-info/METADATA
claritycore-0.0.4.dist-info/WHEEL
claritycore-0.0.4.dist-info/entry_points.txt
claritycore-0.0.4.dist-info/licenses/LICENSE
claritycore-0.0.4.dist-info/RECORD
