Metadata-Version: 2.4
Name: claritycore
Version: 0.0.4
Summary: Next-generation Open Source toolkit for low-level vision. Engineered for state-of-the-art performance in image and video restoration, including Super-Resolution, Denoising, Deblurring, and more.
Project-URL: Homepage, https://github.com/Bezdarnost/claritycore
Project-URL: Repository, https://github.com/Bezdarnost/claritycore
Author-email: Aman Urumbekov <amanurumbekov@gmail.com>
License-File: LICENSE
Keywords: computer-vision,deblurring,denoising,image-restoration,super-resolution,video-restoration
Classifier: License :: OSI Approved :: Apache Software License
Classifier: Operating System :: OS Independent
Classifier: Programming Language :: Python :: 3
Classifier: Topic :: Scientific/Engineering :: Image Processing
Requires-Python: >=3.10
Requires-Dist: hydra-core>=1.3.2
Requires-Dist: loguru>=0.7.3
Requires-Dist: torch>=2.7.0
Requires-Dist: torchvision>=0.22.0
Provides-Extra: dev
Requires-Dist: pre-commit; extra == 'dev'
Requires-Dist: pytest; extra == 'dev'
Requires-Dist: ruff; extra == 'dev'
Requires-Dist: yamlfix; extra == 'dev'
